{
  "/_global-error/page": "app/_global-error/page.js",
  "/_not-found/page": "app/_not-found/page.js",
  "/api/activity/route": "app/api/activity/route.js",
  "/api/admin/adjust-balance/route": "app/api/admin/adjust-balance/route.js",
  "/api/admin/deposits/route": "app/api/admin/deposits/route.js",
  "/api/admin/overview/route": "app/api/admin/overview/route.js",
  "/api/admin/p2p-disputes/route": "app/api/admin/p2p-disputes/route.js",
  "/api/admin/p2p/route": "app/api/admin/p2p/route.js",
  "/api/admin/payment-wallets/route": "app/api/admin/payment-wallets/route.js",
  "/api/admin/settings/route": "app/api/admin/settings/route.js",
  "/api/admin/trades/route": "app/api/admin/trades/route.js",
  "/api/admin/users/[id]/route": "app/api/admin/users/[id]/route.js",
  "/api/admin/users/route": "app/api/admin/users/route.js",
  "/api/admin/verifications/route": "app/api/admin/verifications/route.js",
  "/api/admin/withdrawals/route": "app/api/admin/withdrawals/route.js",
  "/api/auth/change-password/route": "app/api/auth/change-password/route.js",
  "/api/auth/forgot-password/route": "app/api/auth/forgot-password/route.js",
  "/api/auth/google/route": "app/api/auth/google/route.js",
  "/api/auth/login/route": "app/api/auth/login/route.js",
  "/api/auth/logout/route": "app/api/auth/logout/route.js",
  "/api/auth/me/route": "app/api/auth/me/route.js",
  "/api/auth/reset-password/route": "app/api/auth/reset-password/route.js",
  "/api/auth/signup/route": "app/api/auth/signup/route.js",
  "/api/auth/update-email/route": "app/api/auth/update-email/route.js",
  "/api/auth/update-phone/route": "app/api/auth/update-phone/route.js",
  "/api/auth/update-profile/route": "app/api/auth/update-profile/route.js",
  "/api/auth/verify-email/confirm/route": "app/api/auth/verify-email/confirm/route.js",
  "/api/auth/verify-email/send/route": "app/api/auth/verify-email/send/route.js",
  "/api/auth/verify-otp/route": "app/api/auth/verify-otp/route.js",
  "/api/auth/verify-phone/confirm/route": "app/api/auth/verify-phone/confirm/route.js",
  "/api/auth/verify-phone/send/route": "app/api/auth/verify-phone/send/route.js",
  "/api/auth/verify-reset/route": "app/api/auth/verify-reset/route.js",
  "/api/deposits/confirm/route": "app/api/deposits/confirm/route.js",
  "/api/deposits/create/route": "app/api/deposits/create/route.js",
  "/api/deposits/route": "app/api/deposits/route.js",
  "/api/login-history/route": "app/api/login-history/route.js",
  "/api/notifications/auth/route": "app/api/notifications/auth/route.js",
  "/api/notifications/delete/route": "app/api/notifications/delete/route.js",
  "/api/notifications/read-all/route": "app/api/notifications/read-all/route.js",
  "/api/notifications/read/route": "app/api/notifications/read/route.js",
  "/api/notifications/route": "app/api/notifications/route.js",
  "/api/notifications/ws-token/route": "app/api/notifications/ws-token/route.js",
  "/api/p2p/cleanup-expired/route": "app/api/p2p/cleanup-expired/route.js",
  "/api/p2p/messages/route": "app/api/p2p/messages/route.js",
  "/api/p2p/offers/mine/route": "app/api/p2p/offers/mine/route.js",
  "/api/p2p/offers/route": "app/api/p2p/offers/route.js",
  "/api/p2p/reviews/route": "app/api/p2p/reviews/route.js",
  "/api/p2p/trades/route": "app/api/p2p/trades/route.js",
  "/api/p2p/user/route": "app/api/p2p/user/route.js",
  "/api/payment-methods/route": "app/api/payment-methods/route.js",
  "/api/payment-methods/seed/route": "app/api/payment-methods/seed/route.js",
  "/api/price-alerts/check/route": "app/api/price-alerts/check/route.js",
  "/api/price-alerts/route": "app/api/price-alerts/route.js",
  "/api/referrals/route": "app/api/referrals/route.js",
  "/api/route": "app/api/route.js",
  "/api/seed/route": "app/api/seed/route.js",
  "/api/settings/notifications/route": "app/api/settings/notifications/route.js",
  "/api/settings/route": "app/api/settings/route.js",
  "/api/trades/route": "app/api/trades/route.js",
  "/api/transactions/route": "app/api/transactions/route.js",
  "/api/withdrawals/route": "app/api/withdrawals/route.js",
  "/help/page": "app/help/page.js",
  "/learn/[slug]/page": "app/learn/[slug]/page.js",
  "/learn/page": "app/learn/page.js",
  "/notifications/page": "app/notifications/page.js",
  "/page": "app/page.js",
  "/privacy/page": "app/privacy/page.js",
  "/profile/page": "app/profile/page.js",
  "/robots.txt/route": "app/robots.txt/route.js",
  "/security/page": "app/security/page.js",
  "/sitemap.xml/route": "app/sitemap.xml/route.js",
  "/terms/page": "app/terms/page.js",
  "/transactions/page": "app/transactions/page.js"
}